vegans/GAN.py
vegans/__init__.py
vegans/mmgan.py
vegans/wgan.py
vegans/wgan_gp.py
vegans/models/__init__.py
vegans/models/conditional/AbstractConditionalGAN1v1.py
vegans/models/conditional/AbstractConditionalGANGAE.py
vegans/models/conditional/AbstractConditionalGenerativeModel.py
vegans/models/conditional/ConditionalAAE.py
vegans/models/conditional/ConditionalBicycleGAN.py
vegans/models/conditional/ConditionalCycleGAN.py
vegans/models/conditional/ConditionalEBGAN.py
vegans/models/conditional/ConditionalInfoGAN.py
vegans/models/conditional/ConditionalKLGAN.py
vegans/models/conditional/ConditionalLRGAN.py
vegans/models/conditional/ConditionalLSGAN.py
vegans/models/conditional/ConditionalPix2Pix.py
vegans/models/conditional/ConditionalVAEGAN.py
vegans/models/conditional/ConditionalVanillaGAN.py
vegans/models/conditional/ConditionalVanillaVAE.py
vegans/models/conditional/ConditionalWassersteinGAN.py
vegans/models/conditional/ConditionalWassersteinGANGP.py
vegans/models/conditional/__init__.py
vegans/models/unconditional/AAE.py
vegans/models/unconditional/AbstractGAN1v1.py
vegans/models/unconditional/AbstractGANGAE.py
vegans/models/unconditional/AbstractGenerativeModel.py
vegans/models/unconditional/BicycleGAN.py
vegans/models/unconditional/EBGAN.py
vegans/models/unconditional/InfoGAN.py
vegans/models/unconditional/KLGAN.py
vegans/models/unconditional/LRGAN.py
vegans/models/unconditional/LSGAN.py
vegans/models/unconditional/VAEGAN.py
vegans/models/unconditional/VanillaGAN.py
vegans/models/unconditional/VanillaVAE.py
vegans/models/unconditional/WassersteinGAN.py
vegans/models/unconditional/WassersteinGANGP.py
vegans/models/unconditional/__init__.py
vegans/tests/__init__.py
vegans/utils/__init__.py
vegans/utils/layers.py
vegans/utils/loading.py
vegans/utils/losses.py
vegans/utils/networks.py
vegans/utils/plot2DModel.py
vegans/utils/plotting.py
vegans/utils/processing.py
vegans/utils/torchsummary.py
vegans/utils/training.py
vegans/utils/utils.py
vegans-0.4.0.dist-info/LICENSE
vegans-0.4.0.dist-info/METADATA
vegans-0.4.0.dist-info/WHEEL
vegans-0.4.0.dist-info/top_level.txt
vegans-0.4.0.dist-info/RECORD
