Metadata-Version: 2.1
Name: vegans
Version: 0.4.0
Summary: A library to easily train various existing GANs in PyTorch.
Home-page: https://github.com/unit8co/vegans/
Author: Unit8
Author-email: julien@unit8.co
License: MIT
Keywords: gan gans pytorch generative models adversarial networks Wasserstein GAN InfoGAN CycleGAN BicycleGAN VAE AAE
Platform: UNKNOWN
Requires-Python: >=3.7
License-File: LICENSE
Requires-Dist: matplotlib (==3.3.4)
Requires-Dist: numpy (==1.19.5)
Requires-Dist: pandas (==1.1.5)
Requires-Dist: torch (==1.8.1)
Requires-Dist: tensorboard (==2.5.0)
Requires-Dist: torchvision (==0.9.1)
Requires-Dist: wget (==3.2)
